{
  "src/routes/v3/+page.css": {
    "file": "_app/immutable/assets/_page-f1438e97.css",
    "src": "src/routes/v3/+page.css"
  },
  "AttractionTableChoice.css": {
    "file": "_app/immutable/assets/AttractionTableChoice-e1a75a2c.css",
    "src": "AttractionTableChoice.css"
  },
  "_index-ffa1d1d4.js": {
    "file": "_app/immutable/chunks/index-ffa1d1d4.js"
  },
  "_paths-b4419565.js": {
    "file": "_app/immutable/chunks/paths-b4419565.js"
  },
  "node_modules/@sveltejs/kit/src/runtime/client/start.js": {
    "file": "_app/immutable/start-23c06cb9.js",
    "src": "node_modules/@sveltejs/kit/src/runtime/client/start.js",
    "isEntry": true,
    "imports": [
      "_index-ffa1d1d4.js",
      "_singletons-220e94e0.js",
      "_preload-helper-41c905a7.js",
      "_paths-b4419565.js"
    ],
    "dynamicImports": [
      ".svelte-kit/generated/nodes/0.js",
      ".svelte-kit/generated/nodes/1.js",
      ".svelte-kit/generated/nodes/2.js",
      ".svelte-kit/generated/nodes/3.js"
    ]
  },
  ".svelte-kit/generated/nodes/1.js": {
    "file": "_app/immutable/chunks/1-21609e4f.js",
    "src": ".svelte-kit/generated/nodes/1.js",
    "isDynamicEntry": true,
    "imports": [
      "node_modules/@sveltejs/kit/src/runtime/components/error.svelte"
    ]
  },
  ".svelte-kit/generated/nodes/2.js": {
    "file": "_app/immutable/chunks/2-3e8ca16e.js",
    "src": ".svelte-kit/generated/nodes/2.js",
    "isDynamicEntry": true,
    "imports": [
      "src/routes/+page.svelte"
    ]
  },
  ".svelte-kit/generated/nodes/3.js": {
    "file": "_app/immutable/chunks/3-35bb2bea.js",
    "src": ".svelte-kit/generated/nodes/3.js",
    "isDynamicEntry": true,
    "imports": [
      "src/routes/v3/+page.svelte"
    ]
  },
  "src/routes/+layout.js": {
    "file": "_app/immutable/modules/pages/_layout.js-9cbb603b.js",
    "src": "src/routes/+layout.js",
    "isEntry": true,
    "imports": [
      "__layout-da46b06b.js"
    ]
  },
  "src/lib/components/SimulationV3/engine/simulation.worker.ts?worker": {
    "file": "_app/immutable/chunks/simulation.worker-f2100e46.js",
    "src": "src/lib/components/SimulationV3/engine/simulation.worker.ts?worker",
    "isDynamicEntry": true
  },
  "src/routes/+page.svelte": {
    "file": "_app/immutable/components/pages/_page.svelte-696432bf.js",
    "src": "src/routes/+page.svelte",
    "isEntry": true,
    "imports": [
      "_index-ffa1d1d4.js",
      "_AttractionTableChoice-db9eeac0.js"
    ],
    "css": [
      "_app/immutable/assets/_page-f1438e97.css"
    ]
  },
  "_preload-helper-41c905a7.js": {
    "file": "_app/immutable/chunks/preload-helper-41c905a7.js"
  },
  "src/routes/+layout.svelte": {
    "file": "_app/immutable/components/pages/_layout.svelte-a3920ef6.js",
    "src": "src/routes/+layout.svelte",
    "isEntry": true,
    "imports": [
      "_index-ffa1d1d4.js",
      "_paths-b4419565.js"
    ]
  },
  "node_modules/@sveltejs/kit/src/runtime/components/error.svelte": {
    "file": "_app/immutable/components/error.svelte-f2c273bf.js",
    "src": "node_modules/@sveltejs/kit/src/runtime/components/error.svelte",
    "isEntry": true,
    "imports": [
      "_index-ffa1d1d4.js",
      "_singletons-220e94e0.js"
    ]
  },
  ".svelte-kit/generated/nodes/0.js": {
    "file": "_app/immutable/chunks/0-af235a03.js",
    "src": ".svelte-kit/generated/nodes/0.js",
    "isDynamicEntry": true,
    "imports": [
      "__layout-da46b06b.js",
      "src/routes/+layout.svelte"
    ]
  },
  "_AttractionTableChoice-db9eeac0.js": {
    "file": "_app/immutable/chunks/AttractionTableChoice-db9eeac0.js",
    "imports": [
      "_index-ffa1d1d4.js"
    ],
    "css": [
      "_app/immutable/assets/AttractionTableChoice-e1a75a2c.css"
    ]
  },
  "__layout-da46b06b.js": {
    "file": "_app/immutable/chunks/_layout-da46b06b.js"
  },
  "src/routes/v3/+page.svelte": {
    "file": "_app/immutable/components/pages/v3/_page.svelte-c017c241.js",
    "src": "src/routes/v3/+page.svelte",
    "isEntry": true,
    "imports": [
      "_index-ffa1d1d4.js",
      "_preload-helper-41c905a7.js",
      "_AttractionTableChoice-db9eeac0.js"
    ],
    "dynamicImports": [
      "src/lib/components/SimulationV3/engine/simulation.worker.ts?worker"
    ],
    "css": [
      "_app/immutable/assets/_page-f1438e97.css"
    ]
  },
  "_singletons-220e94e0.js": {
    "file": "_app/immutable/chunks/singletons-220e94e0.js",
    "imports": [
      "_index-ffa1d1d4.js",
      "_paths-b4419565.js"
    ]
  },
  "src/routes/+page.css": {
    "file": "_app/immutable/assets/_page-f1438e97.css",
    "src": "src/routes/v3/+page.css"
  }
}